{
  "className": "Part",
  "properties": {
    "Anchored": true,
    "BackSurface": "Weld",
    "BottomSurface": "Weld",
    "CFrame": [-2.9995, 5.3171, 71.1449, 1, 0, 0, 0, 0.9659, -0.2588, 0, 0.2588, 0.9659],
    "Color": [245, 205, 48],
    "CustomPhysicalProperties": {
      "density": 0.0001,
      "friction": 0.0,
      "elasticity": 0.0,
      "frictionWeight": 0.0,
      "elasticityWeight": 0.0,
      "acousticAbsorption": 1.0
    },
    "FormFactor": "Symmetric",
    "LeftSurface": "Weld",
    "RightSurface": "Weld",
    "Size": [2, 1, 1],
    "TopSurface": "Weld"
  }
}
