{
  "className": "ParticleEmitter",
  "properties": {
    "Color": [{
        "time": 0.0,
        "color": [0.2, 0.6, 1.0]
      }, {
        "time": 1.0,
        "color": [0.0, 0.3, 0.8]
      }],
    "LightEmission": 0.8,
    "Rate": 40,
    "Size": [{
        "time": 0.0,
        "value": 0.6,
        "envelope": 0.0
      }, {
        "time": 1.0,
        "value": 0.0,
        "envelope": 0.0
      }],
    "Transparency": [{
        "time": 0.0,
        "value": 0.0,
        "envelope": 0.0
      }, {
        "time": 0.7,
        "value": 0.0,
        "envelope": 0.0
      }, {
        "time": 1.0,
        "value": 1.0,
        "envelope": 0.0
      }]
  }
}
